<?xml version="1.0" encoding="utf-8" ?>
<!DOCTYPE hibernate-mapping PUBLIC
        "-//Hibernate/HibernateMappingDTD5.3//EN"
        "http://www.hibernate.org/dtd/hibernate-mapping-3.0.dtd">
<hibernate-mapping>
    <class name="hibernate.Modulo" table="Modulos" catalog="M06">

        <!--<class name="hibernate.Modulo" table="Modulos" catalog="u787976333_ilerna">  TODO: para usar con bbdd externa-->
            <id name="id">
                <column name="id"/>
                <generator class="assigned"></generator>
            </id>
            <property name="nombre"/>
            <property name="codigo"/>
        </class>
    </hibernate-mapping>